pizzly/__init__.py
pizzly/__version__.py
pizzly/_enums.py
pizzly/core/__init__.py
pizzly/core/indicator.py
pizzly/core/provider.py
pizzly/core/registry.py
pizzly/data/__init__.py
pizzly/data/alpaca.py
pizzly/data/registry.py
pizzly/indicators/__init__.py
pizzly/indicators/bollinger.py
pizzly/indicators/registry.py
pizzly/indicators/rsi.py
pizzly/models/__init__.py
pizzly/models/tools.py
pizzly/tools/__init__.py
pizzly/tools/financial_tool.py
pizzly/tools/registry.py
pizzly-0.1.2.dist-info/METADATA
pizzly-0.1.2.dist-info/WHEEL
pizzly-0.1.2.dist-info/licenses/LICENSE
pizzly-0.1.2.dist-info/RECORD
