Metadata-Version: 2.4
Name: pizzly
Version: 0.1.2
Summary: Python library for financial market analysis combining traditional technical indicators with LLMs, featuring real-time data processing and AI-powered market insights ⚡️
Project-URL: Homepage, https://github.com/louisbrulenaudet/pizzly
Project-URL: Repository, https://github.com/louisbrulenaudet/pizzly
Author-email: Louis Brulé Naudet <contact@louisbrulenaudet.com>
Maintainer-email: Louis Brulé Naudet <contact@louisbrulenaudet.com>
License: Apache-2.0
License-File: LICENSE
Keywords: AI,RSI,bollinger bands,finance,financial indicators,financial markets,machine learning,market analysis,polars,real-time data,stock market,technical analysis,time series,trading,transformers
Classifier: Development Status :: 3 - Alpha
Classifier: Intended Audience :: Developers
Classifier: Intended Audience :: Financial and Insurance Industry
Classifier: Intended Audience :: Science/Research
Classifier: License :: OSI Approved :: Apache Software License
Classifier: Programming Language :: Python :: 3
Classifier: Programming Language :: Python :: 3.11
Classifier: Topic :: Office/Business :: Financial
Classifier: Topic :: Office/Business :: Financial :: Investment
Classifier: Topic :: Scientific/Engineering :: Artificial Intelligence
Classifier: Topic :: Scientific/Engineering :: Information Analysis
Classifier: Topic :: Software Development :: Libraries :: Python Modules
Requires-Python: >=3.10
Requires-Dist: alpaca-py>=0.38.0
Requires-Dist: polars>=1.22.0
Requires-Dist: pydantic>=2.10.6
Requires-Dist: smolagents>=1.8.1
Provides-Extra: dev
Requires-Dist: pre-commit-uv>=4.1.4; extra == 'dev'
Requires-Dist: pre-commit>=4.1.0; extra == 'dev'
Requires-Dist: pyright>=1.1.392.post0; extra == 'dev'
Requires-Dist: pytest>=8.3.4; extra == 'dev'
Requires-Dist: ruff>=0.9.3; extra == 'dev'
